acace_token_weightor/__init__.py
acace_token_weightor-0.1.1.dist-info/LICENSE
acace_token_weightor-0.1.1.dist-info/METADATA
acace_token_weightor-0.1.1.dist-info/WHEEL
acace_token_weightor-0.1.1.dist-info/RECORD
