Metadata-Version: 2.3
Name: acace_token_weightor
Version: 0.1.1
Summary: Assigns importance weights to tokens using NLP heuristics for compression prioritization.
Author: ACACE Team
Author-email: team@acace.ai
Requires-Python: >=3.8,<4.0
Classifier: Programming Language :: Python :: 3
Classifier: Programming Language :: Python :: 3.8
Classifier: Programming Language :: Python :: 3.9
Classifier: Programming Language :: Python :: 3.10
Classifier: Programming Language :: Python :: 3.11
Classifier: Programming Language :: Python :: 3.12
Classifier: Programming Language :: Python :: 3.13
Requires-Dist: numpy (>=1.26.3,<2.0.0)
